hipies/__init__.py
hipies/cwt.py
hipies/remesh.py
hipies/warp_image.py
xicam.hipies-1.0.0.dist-info/DESCRIPTION.rst
xicam.hipies-1.0.0.dist-info/METADATA
xicam.hipies-1.0.0.dist-info/RECORD
xicam.hipies-1.0.0.dist-info/WHEEL
xicam.hipies-1.0.0.dist-info/metadata.json
xicam.hipies-1.0.0.dist-info/top_level.txt
