Metadata-Version: 2.0
Name: xicam.hipies
Version: 1.0.0
Summary: Xi-cam.SAXS companion functions
Home-page: UNKNOWN
Author: Dinesh Kumar
Author-email: dkumar@lbl.gov
License: UNKNOWN
Platform: UNKNOWN
Requires-Dist: numpy
Requires-Dist: scipy
